h1st/core/__init__.py
h1st/core/context.py
h1st/core/viz.py
h1st/exceptions/__init__.py
h1st/exceptions/exception.py
h1st/h1flow/README.md
h1st/h1flow/__init__.py
h1st/h1flow/h1flow.py
h1st/h1flow/h1step.py
h1st/h1flow/h1step_containable.py
h1st/h1flow/temp_step.py
h1st/h1flow/ui/__init__.py
h1st/h1flow/ui/has_ui.py
h1st/h1flow/ui/has_web_ui.py
h1st/metadata.json
h1st/model/README.md
h1st/model/__init__.py
h1st/model/boolean_model.py
h1st/model/ensemble/__init__.py
h1st/model/ensemble/classifier_stack_ensemble.py
h1st/model/ensemble/classifier_stack_ensemble_modeler.py
h1st/model/ensemble/ensemble.py
h1st/model/ensemble/ensemble_modeler.py
h1st/model/ensemble/stack_ensemble.py
h1st/model/ensemble/stack_ensemble_modeler.py
h1st/model/fuzzy/__init__.py
h1st/model/fuzzy/enums.py
h1st/model/fuzzy/fuzzy_model.py
h1st/model/fuzzy/fuzzy_modeler.py
h1st/model/fuzzy/fuzzy_rules.py
h1st/model/fuzzy/fuzzy_variables.py
h1st/model/kswe/__init__.py
h1st/model/kswe/ensemble.py
h1st/model/kswe/kswe.py
h1st/model/kswe/kswe_modeler.py
h1st/model/kswe/segmentor.py
h1st/model/kswe/sub_model_modeler.py
h1st/model/ml_model.py
h1st/model/ml_modeler.py
h1st/model/model.md
h1st/model/model.py
h1st/model/modelable.py
h1st/model/modeler.py
h1st/model/oracle/__init__.py
h1st/model/oracle/ensemble.py
h1st/model/oracle/oracle.py
h1st/model/oracle/oracle_modeler.py
h1st/model/oracle/student.py
h1st/model/oracle/teacher.py
h1st/model/oracle/ts_oracle.py
h1st/model/oracle/ts_oracle_modeler.py
h1st/model/predictive_model.py
h1st/model/repository/__init__.py
h1st/model/repository/explorer.py
h1st/model/repository/model_repository.py
h1st/model/repository/storage/base.py
h1st/model/repository/storage/local.py
h1st/model/repository/storage/s3.py
h1st/model/rule_based_model.py
h1st/model/rule_based_modeler.py
h1st/trust/__init__.py
h1st/trust/auditable.py
h1st/trust/debiasable.py
h1st/trust/decision.py
h1st/trust/describable.py
h1st/trust/describer.py
h1st/trust/enums.py
h1st/trust/explainable.py
h1st-0.1.13.dist-info/LICENSE
h1st-0.1.13.dist-info/WHEEL
h1st-0.1.13.dist-info/METADATA
h1st-0.1.13.dist-info/RECORD
