Metadata-Version: 2.1
Name: h1st
Version: 0.1.13
Summary: Human-First AI (H1st)
Home-page: https://h1st.ai
License: Apache-2.0
Author: Aitomatic, Inc.
Author-email: engineering@aitomatic.com
Requires-Python: >=3.8,<3.11
Classifier: License :: OSI Approved :: Apache Software License
Classifier: Programming Language :: Python :: 3
Classifier: Programming Language :: Python :: 3.10
Classifier: Programming Language :: Python :: 3.8
Classifier: Programming Language :: Python :: 3.9
Requires-Dist: click (>=8.0.4)
Requires-Dist: fsspec (>=2022.8.2)
Requires-Dist: graphviz (>=0.20.1)
Requires-Dist: lime (>=0.2.0.1)
Requires-Dist: numpy (>=1.22.4)
Requires-Dist: pandas (>=1.5.0)
Requires-Dist: pyarrow (>=9.0.0)
Requires-Dist: python-dotenv (>=0.21.0)
Requires-Dist: pyyaml (>=6.0)
Requires-Dist: ruamel.yaml (>=0.17.21)
Requires-Dist: s3fs (>=2022.8.2)
Requires-Dist: scikit-fuzzy (>=0.4.2)
Requires-Dist: scikit-learn (>=1.1.2)
Requires-Dist: shap (>=0.41.0)
Requires-Dist: tensorflow (>=2.10.0)
Requires-Dist: tqdm (>=4.64.1)
Requires-Dist: ulid-py (>=1.1.0)
Project-URL: Repository, https://github.com/h1st-ai/h1st
